pyautolabnova/__init__.py
pyautolabnova/base.py
pyautolabnova/constants.py
pyautolabnova/directfunctions.py
pyautolabnova/fixedCurrentExperiment.py
pyautolabnova/generalfunctions.py
pyautolabnova/setup.py
pyautolabnova/test1.py
pyautolabnova/utilities.py
pyautolabnova/examples/__init__.py
pyautolabnova/resource_files/ADC (A).vi
pyautolabnova/resource_files/ADC (B).vi
pyautolabnova/resource_files/ADC Example (A).vi
pyautolabnova/resource_files/ADC Example (B).vi
pyautolabnova/resource_files/Autolab Complete Example (A).vi
pyautolabnova/resource_files/Autolab Complete Example (B).vi
pyautolabnova/resource_files/Autolab.aliases
pyautolabnova/resource_files/Autolab.llb
pyautolabnova/resource_files/Autolab.lvlps
pyautolabnova/resource_files/Autolab.lvproj
pyautolabnova/resource_files/Avantes.dll
pyautolabnova/resource_files/BlackList.xml
pyautolabnova/resource_files/Connect.vi
pyautolabnova/resource_files/DAC (A).vi
pyautolabnova/resource_files/DAC (B).vi
pyautolabnova/resource_files/DAC Example (A).vi
pyautolabnova/resource_files/DAC Example (B).vi
pyautolabnova/resource_files/DIO (A).vi
pyautolabnova/resource_files/DIO (B).vi
pyautolabnova/resource_files/DIO Example (A).vi
pyautolabnova/resource_files/DIO Example (B).vi
pyautolabnova/resource_files/EI (A).vi
pyautolabnova/resource_files/EI (B).vi
pyautolabnova/resource_files/EI Example (A).vi
pyautolabnova/resource_files/EI Example (B).vi
pyautolabnova/resource_files/EcoChemie.Autolab.Sdk.dll
pyautolabnova/resource_files/EcoChemie.Autolab.Sdk.tlb
pyautolabnova/resource_files/EcoChemie.Shared100.dll
pyautolabnova/resource_files/EcoChemie100.dll
pyautolabnova/resource_files/EcoChemie100.dll.config
pyautolabnova/resource_files/FRA example (A).vi
pyautolabnova/resource_files/FRA.vi
pyautolabnova/resource_files/Infralution.Common.dll
pyautolabnova/resource_files/Infralution.Controls.VirtualTree.dll
pyautolabnova/resource_files/Infralution.Controls.dll
pyautolabnova/resource_files/Infralution.RichText.dll
pyautolabnova-0.1.0a1.dist-info/LICENSE
pyautolabnova-0.1.0a1.dist-info/METADATA
pyautolabnova-0.1.0a1.dist-info/WHEEL
pyautolabnova-0.1.0a1.dist-info/top_level.txt
pyautolabnova-0.1.0a1.dist-info/RECORD
