Metadata-Version: 2.1
Name: pyautolabnova
Version: 0.1.0a1
Summary: A python package for interfacing with Metrohm Autolab instruments
Home-page: https://github.com/yawsnr/pyautolabnova
Author: Dr. Yaw Ofosu Ansong Snr
Author-email: yaw.srr@gmail.com
Classifier: Development Status :: 3 - Alpha
Classifier: Intended Audience :: Science/Research
Classifier: License :: OSI Approved :: MIT License
Classifier: Operating System :: Microsoft :: Windows
Classifier: Programming Language :: Python :: 3
Classifier: Programming Language :: Python :: 3.7
Classifier: Programming Language :: Python :: 3.8
Classifier: Programming Language :: Python :: 3.9
Requires-Python: >=3.7
License-File: LICENSE
Requires-Dist: pythonnet (>=3.0.0)
